exemplary/__init__.py
exemplary/__main__.py
exemplary/cli.py
exemplary/cli_config.py
exemplary/config.py
exemplary/generator.py
exemplary/py.typed
exemplary/scanner.py
exemplary/segment.py
exemplary/processors/__init__.py
exemplary/processors/_all_builtins.py
exemplary/processors/_processor_pool.py
exemplary/processors/base.py
exemplary/processors/fence.py
exemplary/processors/md.py
exemplary/processors/python.py
python_exemplary-0.0.4.dist-info/LICENSE
python_exemplary-0.0.4.dist-info/METADATA
python_exemplary-0.0.4.dist-info/WHEEL
python_exemplary-0.0.4.dist-info/entry_points.txt
python_exemplary-0.0.4.dist-info/top_level.txt
python_exemplary-0.0.4.dist-info/RECORD
