Metadata-Version: 2.1
Name: python-exemplary
Version: 0.0.4
Summary: Embed your documentation inside runnable examples
Home-page: https://github.com/shacham6/exemplary
Author: Shacham Ginat
Author-email: shacham6@gmail.com
License: MIT license
Classifier: Programming Language :: Python :: 3
Classifier: Programming Language :: Python :: 3.8
Classifier: Programming Language :: Python :: 3.9
Classifier: Programming Language :: Python :: 3.10
License-File: LICENSE
Requires-Dist: pyyaml
Requires-Dist: pydantic
Requires-Dist: click
Requires-Dist: rich
Requires-Dist: rich-click
